rayim/__init__.py
rayim/rayim.py
rayim-1.8.4.dist-info/LICENSE
rayim-1.8.4.dist-info/METADATA
rayim-1.8.4.dist-info/WHEEL
rayim-1.8.4.dist-info/entry_points.txt
rayim-1.8.4.dist-info/RECORD
