Metadata-Version: 2.1
Name: rayim
Version: 1.8.4
Summary: Fast image compression for large number of images with Ray library
License: MIT
Author: Mohammad Alyetama
Author-email: malyetama@pm.me
Requires-Python: >=3.7,<4.0
Classifier: License :: OSI Approved :: MIT License
Classifier: Programming Language :: Python :: 3
Classifier: Programming Language :: Python :: 3.7
Classifier: Programming Language :: Python :: 3.8
Classifier: Programming Language :: Python :: 3.9
Classifier: Programming Language :: Python :: 3.10
Classifier: Programming Language :: Python :: 3.11
Classifier: Programming Language :: Python :: 3.12
Requires-Dist: Pillow (>=8.1,<9.0)
Requires-Dist: tqdm (>=4.6,<5.0)
